src/datamem.v
//BUSTY BITS
//Calalan, Sherwin
//Chua, Kyle
//Cruz, Miguel
//Tirona, Paul
`timescale 1ns/1ps
module datamem(clk, data_addr, data_wr, data_in, data_out);
input wire clk;
input wire [31:0] data_addr, data_out;
input wire data_wr;
output reg [31:0] data_in;
reg [7:0] memory [0:1023];

//Initialize data memory
initial begin 
	$readmemh("datamem.txt",memory);
end

//Read
always @ (data_addr) begin
	data_in[31:24] <= memory[data_addr];
	data_in[23:16] <= memory[data_addr+1];
	data_in[15:8] <= memory[data_addr+2];
	data_in[7:0] <= memory[data_addr+3];
end

//Write
always @ (posedge clk) begin
	if(data_wr == 1'b1) begin
		memory[data_addr] <= data_out[31:24];
		memory[data_addr+1] <= data_out[23:16];
		memory[data_addr+2] <= data_out[15:8];
		memory[data_addr+3] <= data_out[7:0];
	end
end
endmodule

src/instmem.v
//BUSTY BITS
//Calalan, Sherwin
//Chua, Kyle
//Cruz, Miguel
//Tirona, Paul
`timescale 1ns/1ps
module instmem(inst_addr, inst);
input wire [31:0] inst_addr;
output reg [31:0] inst;
reg [7:0] instructions [0:1023];

//Initialize instruction memory
initial begin 
	$readmemh("source1.byte",instructions);
end

//Get instruction
always @ (inst_addr) begin
	inst[31:24] <= instructions[inst_addr];
	inst[23:16] <= instructions[inst_addr+1];
	inst[15:8] <= instructions[inst_addr+2];
	inst[7:0] <= instructions[inst_addr+3];
end
endmodule

src/single_cycle_mips.v
//BUSTY BITS
//Calalan, Sherwin
//Chua, Kyle
//Cruz, Miguel
//Tirona, Paul
`timescale 1ns/1ps
module single_cycle_mips(clk, rst_n, inst_addr, inst, data_addr, data_in, data_out, data_wr);

input wire clk, rst_n;
output reg [31:0] inst_addr;				//Program Counter
input wire [31:0] inst;						//Instruction opcode in binary
output reg [31:0] data_addr, data_out;		//Memory address na paglalagyan ng data; Data na iwriwrite to memory
input wire [31:0] data_in;					//Data na irearead from memory
output reg data_wr;							//Write enable

reg jump;
reg [5:0] opcode;
reg [4:0] indexS;
reg [4:0] indexT;
reg [4:0] indexD;
reg [31:0] imm;
reg [31:0] temp = 32'd0;
reg [31:0] registers [31:0];
integer ctr;
  
initial begin
	inst_addr <= 32'd0;
	data_wr <= 1'b0;
	
	for(ctr=0; ctr<32; ctr++) begin
		registers[ctr] <= 32'd0;
	end
	
	jump = 1'b0;
end

always @ (negedge rst_n) begin	//Reset trigger
	inst_addr <= 32'd0;
	
	for(ctr=0; ctr<32; ctr++) begin
		registers[ctr] <= 32'd0;
	end
	
	data_wr <= 1'b0;
	jump <= 1'b0;
end

always @ (negedge clk) begin	//Increment program counter after every clock cycle
	if(jump == 1'b0) begin
		inst_addr <= inst_addr + 32'd4;
	end
end

always @ (inst_addr) begin 		//Execute when clock is postive edge
	data_wr <= 1'b0;
	#1 opcode[5:0] <= inst[31:26];
	#1 indexS[4:0] <= inst[25:21];
	#1 indexT[4:0] <= inst[20:16];
	#1 indexD[4:0] <= inst[15:11];
	#1 imm = {inst[15], inst[15], inst[15], inst[15], inst[15], inst[15], inst[15], inst[15], inst[15], inst[15], inst[15], inst[15], inst[15], inst[15], inst[15], inst[15], inst[15:0]};

	//ADDITION/SUBTRACTION/SLT
	if(opcode == 6'b000000) begin
		opcode = inst[5:0];
		jump <= 1'b0;
		//ADD
		if(opcode == 6'b100000) begin
			registers[indexD] = registers[indexS] + registers[indexT];	
		end
		
		//SUB
		else if(opcode == 6'b100010) begin
			registers[indexD] = registers[indexS] - registers[indexT];
		end
		
		//SLT
		else if(opcode == 6'b101010) begin
			if(registers[indexS] > registers[indexT]) begin							
				registers[indexD] = 32'd1;  //set rd to 32'd1
			end
		
			else begin		
				registers[indexD] = 32'd0; //set rd to 32'd0
			end
		end
	end
	
	//LW
	else if(opcode == 6'b100011) begin
		temp = registers[indexS] + imm;
		data_addr = temp;
		#1 registers[indexT] = data_in;
		jump <= 1'b0;	
	end
	
	//SW
	else if(opcode == 6'b101011) begin
		temp = registers[indexS] + imm;
		data_addr = temp;
		data_out = registers[indexT];	
		#2 data_wr <= 1'b1;
		jump = 1'b0;		
	end
	
	//BEQ
	else if(opcode == 6'b000100) begin	
		if(registers[indexS] == registers[indexT]) begin
			inst_addr <= inst_addr + imm*4 + 32'd4;
			jump <= 1'b1;
		end
		
		else begin
			jump <= 1'b0;
		end		
	end
	
	//BNE
	else if(opcode == 6'b000101) begin
		if(registers[indexS] != registers[indexT]) begin
			inst_addr <= inst_addr + imm*4 + 32'd4;
			jump <= 1'b1;
		end
		
		else begin
			jump <= 1'b0;
		end		
	end	
end

endmodule

src/tb_single_cycle_mips.v
`include "single_cycle_mips.v"
`include "instmem.v"
`include "datamem.v"
`timescale 1ns/1ps
`define CLK_PERIOD 50
`define TIMEOUT 9 
`define WATCHDOG 500
module tb_single_cycle_mips;
  
  reg clk,rst_n;
  wire [31:0] inst_addr,inst;
  wire [31:0] data_addr,data_in,data_out;
  wire data_wr;

  single_cycle_mips UUT(
    .clk(clk),
    .rst_n(rst_n),
    .inst_addr(inst_addr),
    .inst(inst),
    .data_addr(data_addr),
    .data_in(data_in),
    .data_out(data_out),
    .data_wr(data_wr)
  );

  instmem INSTMEM(
    .inst_addr(inst_addr),
    .inst(inst)
  );

  datamem DATAMEM(
    .clk(clk),
    .data_addr(data_addr),
    .data_wr(data_wr),
    .data_in(data_in),
    .data_out(data_out)
  );

  always begin
    #(`CLK_PERIOD/2.0) clk = ~clk;
  end

  integer nop_count,watch_count,i;
  integer ldst,add,sub,slt,beq,bne;
  reg [31:0] ref [0:127];
  reg [31:0] res;
  initial begin
	$dumpfile("tb_single_cycle_mips.vcd");
	$dumpvars(0, clk, rst_n, inst_addr, inst, data_addr, data_in, data_out, data_wr);
    //$vcdplusfile("tb_single_cycle_mips.vpd");
    //$vcdpluson;
    

    //init
    clk = 0;
    rst_n = 0;
    nop_count = 0;
    watch_count = 0;

    //#(`CLK_PERIOD*10);
    #(5);
    rst_n = 1'b1;

    //start
    while((nop_count < `TIMEOUT)&&(watch_count < `WATCHDOG))begin
      #(`CLK_PERIOD);
      if (inst == 32'd0)
        nop_count = nop_count + 1;
      else
        nop_count = 0;
      watch_count = watch_count + 1;
    end

    ldst = 0;
    add = 0;
    sub = 0;
    slt = 0;
    beq = 0;
    bne = 0;

    //display mem
    for (i=0; i<22; i=i+1) begin
      /*$display("%X%X%X%X",
        datamem.memory[(i*4)],
        datamem.memory[(i*4)+1],
        datamem.memory[(i*4)+2],
        datamem.memory[(i*4)+3],
        );*/ 
      res = {DATAMEM.memory[(i*4)],
             DATAMEM.memory[(i*4)+1],
             DATAMEM.memory[(i*4)+2],
             DATAMEM.memory[(i*4)+3]};
      case(i)
        3,4,6:
          if (res == ref[i]) ldst = ldst + 1;
        7,8,9,10:
          if (res == ref[i]) add = add + 1;
        11,12,13,14:
          if (res == ref[i]) beq = beq + 1;
        15,16,17,18:
          if (res == ref[i]) sub = sub + 1;
        19,20:
          if (res == ref[i]) slt = slt + 1;
        21:
          if (res == ref[i]) bne = bne + 1;
      endcase
    end

    $display("Load/Store: %d",ldst);
    $display("ADD: %d",add);
    $display("SUB: %d",sub);
    $display("SLT: %d",slt);
    $display("BEQ: %d",beq);
    $display("BNE: %d",bne);
    
    $finish;
  end

  initial begin
    $readmemh("ref.txt",ref);
  end

`ifdef SDF
  initial begin
    $sdf_annotate("../mapped/single_cycle_mips_mapped.sdf",single_cycle_mips);
  end
`endif

endmodule

src/tb_single_cycle_mips.vcd
$date
	Fri Mar 17 11:57:34 2017
$end
$version
	Icarus Verilog
$end
$timescale
	1ps
$end
$scope module tb_single_cycle_mips $end
$var reg 1 ! clk $end
$upscope $end
$scope module tb_single_cycle_mips $end
$var reg 1 " rst_n $end
$upscope $end
$scope module tb_single_cycle_mips $end
$var wire 32 # inst_addr [31:0] $end
$upscope $end
$scope module tb_single_cycle_mips $end
$var wire 32 $ inst [31:0] $end
$upscope $end
$scope module tb_single_cycle_mips $end
$var wire 32 % data_addr [31:0] $end
$upscope $end
$scope module tb_single_cycle_mips $end
$var wire 32 & data_in [31:0] $end
$upscope $end
$scope module tb_single_cycle_mips $end
$var wire 32 ' data_out [31:0] $end
$upscope $end
$scope module tb_single_cycle_mips $end
$var wire 1 ( data_wr $end
$upscope $end
$enddefinitions $end
#0
$dumpvars
0(
bx '
bx &
bx %
b10001100000000010000000000000000 $
b0 #
0"
0!
$end
#5000
b100011010101111001101 &
b0 %
1"
#25000
1!
#50000
b10001100000000100000000000000100 $
b100 #
0!
#55000
b11111111111111110000000100000001 &
b100 %
#75000
1!
#100000
b10001100000000110000000000001000 $
b1000 #
0!
#105000
b100 &
b1000 %
#125000
1!
#150000
b10101100011000100000000000001000 $
b1100 #
0!
#155000
b11111111111111111111111111111000 &
b11111111111111110000000100000001 '
b1100 %
#157000
1(
#175000
1!
#200000
b10101100000000010000000000010000 $
0(
b10000 #
0!
#205000
b0 &
b100011010101111001101 '
b10000 %
#207000
1(
#225000
1!
#250000
b10001100000001000000000000010100 $
0(
b10100 #
0!
#255000
b100000 &
b10100 %
#275000
1!
#300000
b10101100100000111111111111111000 $
b11000 #
0!
#305000
b0 &
b100 '
b11000 %
#307000
1(
#325000
1!
#350000
b1000010010100000100000 $
0(
b11100 #
0!
#375000
1!
#400000
b10000100011000000100000 $
b100000 #
0!
#425000
1!
#450000
b1000100011100000100000 $
b100100 #
0!
#475000
1!
#500000
b10000010100000000100000 $
b101000 #
0!
#525000
1!
#550000
b10101100000001010000000000011100 $
b101100 #
0!
#555000
b1000110101011110011010 '
b11100 %
#557000
1(
#575000
1!
#600000
b10101100000001100000000000100000 $
0(
b110000 #
0!
#605000
b11111111111111100000001000000010 '
b100000 %
#607000
1(
#625000
1!
#650000
b10101100000001110000000000100100 $
0(
b110100 #
0!
#655000
b100001010110011001110 '
b100100 %
#657000
1(
#675000
1!
#700000
b10101100000010000000000000101000 $
0(
b111000 #
0!
#705000
b101000 %
#707000
1(
#725000
1!
#750000
b10001100000010010000000000001000 $
0(
b111100 #
0!
#755000
b100 &
b1000 %
#775000
1!
#800000
b10000011010010000000000000001 $
b1000000 #
0!
#805000
b10101100000000100000000000110000 $
b1001000 #
#810000
b11111111111111111111111111111111 &
b11111111111111110000000100000001 '
b110000 %
#812000
1(
#825000
1!
#850000
b10000011000000000000000000001 $
0(
b1001100 #
0!
#875000
1!
#900000
b10101100000000010000000000110100 $
b1010000 #
0!
#905000
b100011010101111001101 '
b110100 %
#907000
1(
#925000
1!
#950000
b10101100000000010000000000111000 $
0(
b1010100 #
0!
#955000
b111000 %
#957000
1(
#975000
1!
#1000000
b1000010010100000100010 $
0(
b1011000 #
0!
#1025000
1!
#1050000
b10000100011000000100010 $
b1011100 #
0!
#1075000
1!
#1100000
b1000100011100000100010 $
b1100000 #
0!
#1125000
1!
#1150000
b10000010100000000100010 $
b1100100 #
0!
#1175000
1!
#1200000
b10101100000001010000000000111100 $
b1101000 #
0!
#1205000
b1010100 &
b0 '
b111100 %
#1207000
1(
#1225000
1!
#1250000
b10101100000001100000000001000000 $
0(
b1101100 #
0!
#1255000
b11111111111111111111111111111111 &
b1000000 %
#1257000
1(
#1275000
1!
#1300000
b10101100000001110000000001000100 $
0(
b1110000 #
0!
#1305000
b100101010101011001100 '
b1000100 %
#1307000
1(
#1325000
1!
#1350000
b10101100000010000000000001001000 $
0(
b1110100 #
0!
#1355000
b11111111111011010101010100110100 '
b1001000 %
#1357000
1(
#1375000
1!
#1400000
b1000100010100000101010 $
0(
b1111000 #
0!
#1425000
1!
#1450000
b10000010011000000101010 $
b1111100 #
0!
#1475000
1!
#1500000
b10101100000001010000000001001100 $
b10000000 #
0!
#1505000
b0 '
b1001100 %
#1507000
1(
#1525000
1!
#1550000
b10101100000001100000000001010000 $
0(
b10000100 #
0!
#1555000
b1 '
b1010000 %
#1557000
1(
#1575000
1!
#1600000
b10100000111010000000100000 $
0(
b10001000 #
0!
#1625000
1!
#1650000
b100000110010000000100010 $
b10001100 #
0!
#1675000
1!
#1700000
b10100100000001111111111111101 $
b10010000 #
0!
#1705000
b10100000111010000000100000 $
b10001000 #
#1725000
1!
#1750000
b100000110010000000100010 $
b10001100 #
0!
#1775000
1!
#1800000
b10100100000001111111111111101 $
b10010000 #
0!
#1805000
b10100000111010000000100000 $
b10001000 #
#1825000
1!
#1850000
b100000110010000000100010 $
b10001100 #
0!
#1875000
1!
#1900000
b10100100000001111111111111101 $
b10010000 #
0!
#1905000
b10100000111010000000100000 $
b10001000 #
#1925000
1!
#1950000
b100000110010000000100010 $
b10001100 #
0!
#1975000
1!
#2000000
b10100100000001111111111111101 $
b10010000 #
0!
#2005000
b10100000111010000000100000 $
b10001000 #
#2025000
1!
#2050000
b100000110010000000100010 $
b10001100 #
0!
#2075000
1!
#2100000
b10100100000001111111111111101 $
b10010000 #
0!
#2105000
b10100000111010000000100000 $
b10001000 #
#2125000
1!
#2150000
b100000110010000000100010 $
b10001100 #
0!
#2175000
1!
#2200000
b10100100000001111111111111101 $
b10010000 #
0!
#2205000
b10100000111010000000100000 $
b10001000 #
#2225000
1!
#2250000
b100000110010000000100010 $
b10001100 #
0!
#2275000
1!
#2300000
b10100100000001111111111111101 $
b10010000 #
0!
#2305000
b10100000111010000000100000 $
b10001000 #
#2325000
1!
#2350000
b100000110010000000100010 $
b10001100 #
0!
#2375000
1!
#2400000
b10100100000001111111111111101 $
b10010000 #
0!
#2425000
1!
#2450000
b10101100000101000000000001010100 $
b10010100 #
0!
#2455000
b100000 '
b1010100 %
#2457000
1(
#2475000
1!
#2500000
b0 $
0(
b10011000 #
0!
#2525000
1!
#2550000
b10011100 #
0!
#2575000
1!
#2600000
b10100000 #
0!
#2625000
1!
#2650000
b10100100 #
0!
#2675000
1!
#2700000
b10101000 #
0!
#2725000
1!
#2750000
b10101100 #
0!
#2775000
1!
#2800000
b10110000 #
0!
#2825000
1!
#2850000
b10110100 #
0!
#2875000
1!
#2900000
b10111000 #
0!
